Metadata-Version: 2.4
Name: localcosmos_app_kit_taxonomy
Version: 0.2.3
Summary: Local Cosmos Taxonomy django app
Home-page: https://github.com/localcosmos/app-kit
Author: Thomas Uher
Author-email: thomas.uher@sisol-systems.com
License: The MIT License
Keywords: django,localcosmos,localcosmos server,biodiversity,taxonomy
Platform: OS Independent
Classifier: Programming Language :: Python :: 3
Classifier: License :: OSI Approved :: MIT License
Classifier: Operating System :: OS Independent
Requires-Python: >=3.6
License-File: LICENCE
Dynamic: author
Dynamic: author-email
Dynamic: classifier
Dynamic: description
Dynamic: description-content-type
Dynamic: home-page
Dynamic: keywords
Dynamic: license
Dynamic: license-file
Dynamic: platform
Dynamic: requires-python
Dynamic: summary
